canonicalwebteam/__init__.py
canonicalwebteam/sitemaps_parser/__init__.py
canonicalwebteam/sitemaps_parser/app.py
canonicalwebteam_sitemaps_parser-1.0.3.dist-info/LICENSE
canonicalwebteam_sitemaps_parser-1.0.3.dist-info/METADATA
canonicalwebteam_sitemaps_parser-1.0.3.dist-info/WHEEL
canonicalwebteam_sitemaps_parser-1.0.3.dist-info/top_level.txt
canonicalwebteam_sitemaps_parser-1.0.3.dist-info/RECORD
