Metadata-Version: 2.2
Name: canonicalwebteam.sitemaps-parser
Version: 1.0.3
Summary: Flask extension to parse websites and extract structured data to build sitemaps.
Home-page: https://github.com/canonical/canonicalwebteam.sitemaps-parser
Author: Canonical webteam
Author-email: webteam@canonical.com
License-File: LICENSE
Requires-Dist: Flask>=1.0.2
Requires-Dist: beautifulsoup4
Requires-Dist: humanize
Requires-Dist: lxml
Requires-Dist: requests
Requires-Dist: python-dateutil
Requires-Dist: validators
Requires-Dist: python-slugify
Dynamic: author
Dynamic: author-email
Dynamic: description
Dynamic: description-content-type
Dynamic: home-page
Dynamic: requires-dist
Dynamic: summary
